README.rst
setup.cfg
setup.py
tensorcore/__init__.py
tensorcore/_pyutils.py
tensorcore/_version.py
tensorcore/base.py
tensorcore/decomposition.py
tensorcore/dense.py
tensorcore/matrix_operations.py
tensorcore/sparse.py
tensorcore/tensor_operations.py
tensorcore/vector_operations.py
tensorcore.egg-info/PKG-INFO
tensorcore.egg-info/SOURCES.txt
tensorcore.egg-info/dependency_links.txt
tensorcore.egg-info/requires.txt
tensorcore.egg-info/top_level.txt
tensorcore/tests/__init__.py
tensorcore/tests/matrix_operations_test.py
tensorcore/tests/tensor_operations_test.py
tensorcore/tests/tensor_test.py