Metadata-Version: 1.1
Name: tensorcore
Version: 0.2.3
Summary: Multilinear algebra package supporting basic operations on dense and sparse tensors
Home-page: https://gitlab.com/cmick/tensorcore
Author: Michal Ciesielczyk
Author-email: michal.ciesielczyk@put.poznan.pl
License: MIT
Download-URL: https://gitlab.com/cmick/tensorcore/repository/v0.2.3/archive.tar.gz
Platform: UNKNOWN
Classifier: Development Status :: 3 - Alpha
Classifier: Topic :: Scientific/Engineering
Classifier: Intended Audience :: Science/Research
Classifier: License :: OSI Approved :: MIT License
Classifier: Operating System :: OS Independent
Classifier: Programming Language :: Python :: 3 :: Only
Classifier: Programming Language :: Python :: 3.4
Classifier: Programming Language :: Python :: 3.5
Classifier: Programming Language :: Python :: 3.6
